fastcubo/__init__.py
fastcubo/main.py
fastcubo/utils.py
fastcubo-0.1.6.dist-info/LICENSE
fastcubo-0.1.6.dist-info/METADATA
fastcubo-0.1.6.dist-info/WHEEL
fastcubo-0.1.6.dist-info/RECORD
