Metadata-Version: 2.1
Name: fastcubo
Version: 0.1.6
Summary: 🏎💨vroom vroom - data downloader
Home-page: https://github.com/csaybar/fastcubo
Author: Cesar Aybar
Author-email: fcesar.aybar@uv.es
Requires-Python: >=3.9,<4.0
Classifier: Programming Language :: Python :: 3
Classifier: Programming Language :: Python :: 3.9
Classifier: Programming Language :: Python :: 3.10
Classifier: Programming Language :: Python :: 3.11
Classifier: Programming Language :: Python :: 3.12
Requires-Dist: numpy (>=1.25.2)
Requires-Dist: pandas (>=2.0.3)
Requires-Dist: utm (>=0.7.0,<0.8.0)
Project-URL: Documentation, https://csaybar.github.io/fastcubo/
Project-URL: Repository, https://github.com/csaybar/fastcubo
